django_blocknote/__init__.py
django_blocknote/admin.py
django_blocknote/apps.py
django_blocknote/assets.py
django_blocknote/exceptions.py
django_blocknote/helpers.py
django_blocknote/signals.py
django_blocknote/urls.py
django_blocknote/widgets.py
django_blocknote/forms/__init__.py
django_blocknote/forms/forms.py
django_blocknote/forms/mixins.py
django_blocknote/image/__init__.py
django_blocknote/image/remove.py
django_blocknote/image/upload.py
django_blocknote/management/commands/__init__.py
django_blocknote/management/commands/helpers.py
django_blocknote/migrations/0001_initial.py
django_blocknote/migrations/0002_alter_unusedimageurls_image_url.py
django_blocknote/migrations/0003_documenttemplate.py
django_blocknote/migrations/__init__.py
django_blocknote/models/__init__.py
django_blocknote/models/fields.py
django_blocknote/models/models.py
django_blocknote/static/django_blocknote/.vite/manifest.json
django_blocknote/static/django_blocknote/css/blocknote.Bd_f-piI.css
django_blocknote/static/django_blocknote/js/blocknote.C48zuI5V.js
django_blocknote/templates/django_blocknote/blocknote.html
django_blocknote/templatetags/__init__.py
django_blocknote/templatetags/blocknote_tags.py
django_blocknote/views/__init__.py
django_blocknote/views/mixins.py
django_blocknote/views/views.py
django_blocknote-2025.11.11.1.dist-info/licenses/LICENSE
django_blocknote-2025.11.11.1.dist-info/METADATA
django_blocknote-2025.11.11.1.dist-info/WHEEL
django_blocknote-2025.11.11.1.dist-info/top_level.txt
django_blocknote-2025.11.11.1.dist-info/RECORD
