Metadata-Version: 2.4
Name: django-blocknote
Version: 2025.11.11.1
Summary: BlockNote rich text editor integration for Django
Author-email: Mark Sevelj <mark.sevelj@dunwright.com.au>, Ryan Sevelj <ryan.sevelj@dunwright.com.au>
License-Expression: BSD-3-Clause
Project-URL: Homepage, https://github.com/Dunwright-dev/django-blocknote
Project-URL: Documentation, https://django-blocknote.readthedocs.io/
Project-URL: Repository, https://github.com/Dunwright-dev/django-blocknote
Project-URL: Issues, https://github.com/yourusername/django-blocknote/issues
Project-URL: Changelog, https://github.com/Dunwright-dev/django-blocknote/blob/main/CHANGELOG.md
Keywords: django,rich-text-editor,blocknote,wysiwyg
Classifier: Development Status :: 3 - Alpha
Classifier: Environment :: Web Environment
Classifier: Framework :: Django
Classifier: Framework :: Django :: 4.2
Classifier: Framework :: Django :: 5.0
Classifier: Intended Audience :: Developers
Classifier: Operating System :: OS Independent
Classifier: Programming Language :: Python
Classifier: Programming Language :: Python :: 3.11
Classifier: Programming Language :: Python :: 3.12
Classifier: Programming Language :: Python :: 3.13
Classifier: Topic :: Internet :: WWW/HTTP
Classifier: Topic :: Software Development :: Libraries :: Python Modules
Requires-Python: >=3.10
License-File: LICENSE
Requires-Dist: Django>=4.2
Requires-Dist: Pillow
Requires-Dist: filetype
Requires-Dist: structlog
Provides-Extra: docs
Requires-Dist: furo; extra == "docs"
Requires-Dist: pygments-monokai-hcb; extra == "docs"
Requires-Dist: myst-parser; extra == "docs"
Requires-Dist: sphinx; extra == "docs"
Requires-Dist: sphinx-copybutton; extra == "docs"
Requires-Dist: sphinx-inline-tabs; extra == "docs"
Requires-Dist: sphinxcontrib-mermaid; extra == "docs"
Provides-Extra: dev
Requires-Dist: build; extra == "dev"
Requires-Dist: black; extra == "dev"
Requires-Dist: django-extensions; extra == "dev"
Requires-Dist: flake8; extra == "dev"
Requires-Dist: isort; extra == "dev"
Requires-Dist: django-blocknote[docs]; extra == "dev"
Requires-Dist: django-coverage; extra == "dev"
Requires-Dist: djlint; extra == "dev"
Requires-Dist: pytest; extra == "dev"
Requires-Dist: pytest-cov; extra == "dev"
Requires-Dist: pytest-randomly; extra == "dev"
Requires-Dist: pytest-xdist; extra == "dev"
Requires-Dist: ruff; extra == "dev"
Requires-Dist: tblib; extra == "dev"
Requires-Dist: tox; extra == "dev"
Requires-Dist: twine; extra == "dev"
Dynamic: license-file
